pyprojstencil/__init__.py
pyprojstencil/__main__.py
pyprojstencil/command_line.py
pyprojstencil/common.py
pyprojstencil/configure.py
pyprojstencil/copy_tree.py
pyprojstencil/errors.py
pyprojstencil/get_license.py
pyprojstencil/init_git.py
pyprojstencil/init_venv.py
pyprojstencil/read_templates.py
pyprojstencil/templates/INSTALL.rst
pyprojstencil/templates/MANIFEST.in
pyprojstencil/templates/README.rst
pyprojstencil/templates/dot.gitignore
pyprojstencil/templates/dot.gitlab-ci.yml
pyprojstencil/templates/dot.readthedocs.yml
pyprojstencil/templates/pyproject.toml
pyprojstencil/templates/requirements.txt
pyprojstencil/templates/setup.cfg
pyprojstencil/templates/code-aid/build_sphinx.sh
pyprojstencil/templates/code-aid/common.sh
pyprojstencil/templates/code-aid/coverage.sh
pyprojstencil/templates/code-aid/init_venv.sh
pyprojstencil/templates/code-aid/install.sh
pyprojstencil/templates/code-aid/plan.org
pyprojstencil/templates/code-aid/pypi.sh
pyprojstencil/templates/code-aid/requirements.txt
pyprojstencil/templates/docs/INSTALL.rst
pyprojstencil/templates/docs/Makefile
pyprojstencil/templates/docs/README.rst
pyprojstencil/templates/docs/conf.py
pyprojstencil/templates/docs/configure.rst
pyprojstencil/templates/docs/coverage.svg
pyprojstencil/templates/docs/index.rst
pyprojstencil/templates/docs/make.bat
pyprojstencil/templates/docs/requirements.txt
pyprojstencil/templates/docs/source-code-doc.rst
pyprojstencil/templates/docs/usage.rst
pyprojstencil/templates/docs/docs/coverage.svg
pyprojstencil/templates/licenses/Apache
pyprojstencil/templates/licenses/Apache_header
pyprojstencil/templates/licenses/GPLv3
pyprojstencil/templates/licenses/GPLv3_header
pyprojstencil/templates/licenses/LGPLv3
pyprojstencil/templates/licenses/LGPLv3_header
pyprojstencil/templates/licenses/MIT
pyprojstencil/templates/licenses/MIT_header
pyprojstencil/templates/licenses/custom
pyprojstencil/templates/licenses/custom_header
pyprojstencil/templates/src/__init__.py
pyprojstencil-1.0.2.dist-info/LICENSE
pyprojstencil-1.0.2.dist-info/METADATA
pyprojstencil-1.0.2.dist-info/WHEEL
pyprojstencil-1.0.2.dist-info/eager_resources.txt
pyprojstencil-1.0.2.dist-info/entry_points.txt
pyprojstencil-1.0.2.dist-info/namespace_packages.txt
pyprojstencil-1.0.2.dist-info/top_level.txt
pyprojstencil-1.0.2.dist-info/RECORD
