Metadata-Version: 2.1
Name: pyprojstencil
Version: 1.0.2
Summary: pyprojstencil - templates for new python project
Home-page: https://gitlab.com/pradyparanjpe/pyprojstencil.git
Download-URL: 
Author: Pradyumna Paranjape
Author-email: pradyparanjpe@rediffmail.com
License: LGPLv3
Project-URL: Documentation, https://pradyparanjpe.gitlab.io/pyprojstencil
Project-URL: Source_url, https://gitlab.com/pradyparanjpe/pyprojstencil.git
Platform: linux
Classifier: Programming Language :: Python
Classifier: Programming Language :: Python :: 3.8
Classifier: Programming Language :: Python :: 3.9
Classifier: Programming Language :: Python :: 3.10
Classifier: License :: OSI Approved :: GNU Lesser General Public License v3 (LGPLv3)
Provides: pyprojstencil
Requires-Python: >=3.8
License-File: LICENSE
Requires-Dist: argcomplete
Requires-Dist: psprint
Requires-Dist: pyyaml
Requires-Dist: GitPython
Requires-Dist: virtualenv
